Selenium2Screenshots/__init__.py
Selenium2Screenshots/keywords.robot
robotframework_selenium2screenshots-0.8.1.dist-info/DESCRIPTION.rst
robotframework_selenium2screenshots-0.8.1.dist-info/METADATA
robotframework_selenium2screenshots-0.8.1.dist-info/RECORD
robotframework_selenium2screenshots-0.8.1.dist-info/WHEEL
robotframework_selenium2screenshots-0.8.1.dist-info/metadata.json
robotframework_selenium2screenshots-0.8.1.dist-info/top_level.txt
