Metadata-Version: 1.1
Name: robotframework-selenium2screenshots
Version: 0.8.1
Summary: Robot Framework keyword library for capturing annotated screenshots with Selenium2Library
Home-page: https://github.com/datakurre/robotframework-selenium2screenshots/
Author: Asko Soukka
Author-email: asko.soukka@iki.fi
License: GPL
Platform: UNKNOWN
Classifier: Programming Language :: Python
Classifier: Programming Language :: Python :: 2.7
Classifier: Programming Language :: Python :: 3.4
Classifier: Programming Language :: Python :: 3.5
Classifier: Programming Language :: Python :: 3.6
